topo2geo/__init__.py
topo2geo/core.py
topo2geo-0.4.4.dist-info/METADATA
topo2geo-0.4.4.dist-info/WHEEL
topo2geo-0.4.4.dist-info/entry_points.txt
topo2geo-0.4.4.dist-info/top_level.txt
topo2geo-0.4.4.dist-info/RECORD
