Metadata-Version: 2.1
Name: topo2geo
Version: 0.4.4
Summary: CLI for converting TopoJSON files to GeoJSON
Home-page: https://github.com/kylepollina/topo2geo
Author: Kyle Pollina
Author-email: kylepollina@pm.me
License: UNKNOWN
Platform: UNKNOWN
Classifier: Programming Language :: Python :: 3
Classifier: Programming Language :: Python :: 3.7
Requires-Dist: click
Requires-Dist: shapely
